gruvboxsphinx/__init__.py
gruvboxsphinx/footer.html
gruvboxsphinx/layout.html
gruvboxsphinx/menu.html
gruvboxsphinx/search.html
gruvboxsphinx/searchinput.html
gruvboxsphinx/theme.conf
gruvboxsphinx/static/css/gruvbox.css
gruvboxsphinx/static/css/insegel.css
gruvboxsphinx/static/img/favicon-16x16.png
gruvboxsphinx/static/img/favicon-32x32.png
gruvboxsphinx/static/img/logo.svg
gruvboxsphinx-1.3.dist-info/LICENSE
gruvboxsphinx-1.3.dist-info/METADATA
gruvboxsphinx-1.3.dist-info/WHEEL
gruvboxsphinx-1.3.dist-info/entry_points.txt
gruvboxsphinx-1.3.dist-info/top_level.txt
gruvboxsphinx-1.3.dist-info/RECORD
